pyrunnable/__init__.py
pyrunnable-1.0.1.dist-info/METADATA
pyrunnable-1.0.1.dist-info/WHEEL
pyrunnable-1.0.1.dist-info/licenses/LICENSE
pyrunnable-1.0.1.dist-info/RECORD
