Metadata-Version: 2.4
Name: pyrunnable
Version: 1.0.1
Project-URL: Homepage, https://github.com/nbdy/pyrunnable
Project-URL: Repository, https://github.com/nbdy/pyrunnable.git
Project-URL: Issues, https://github.com/nbdy/pyrunnable/issues
Author: nbdy
Maintainer: nbdy
License: MIT License
License-File: LICENSE
Classifier: Development Status :: 4 - Beta
Classifier: License :: OSI Approved :: MIT License
Classifier: Programming Language :: Python :: 3.11
Classifier: Programming Language :: Python :: 3.12
Requires-Python: >=3.6
